[
    {
        "id": 1,
        "name": "ãã¾ã¿ã¡ã‚ƒã‚“",
        "age": 20,
        "prefecture": "ç¦å²¡çœŒ",
        "tweet": "ã‚ˆã‚ã—ããŠé¡˜ã„ã—ã¾ã™ã‚ã¾ã‚Šå‹é”ãŒã„ã¾ã›ã‚“æ°—è»½ã«ã”é€£çµ¡ãã ã•ã„",
        "image": "1"
    },
    {
        "id": 2,
        "name": "ã™ãƒ¼",
        "age": 21,
        "prefecture": "æ±äº¬éƒ½",
        "tweet": "ã“ã‚“ã«ã¡ã¯ã€‚ç”·å¥³å…±ã«ã€ã‚¬ãƒ„ã‚¬ãƒ„ã•ã‚Œã¦ã„ã‚‹æ–¹ã¯è‹¦æ‰‹ã§ã™ã€‚å­¦ç”Ÿãªã®ã§ã€ãŠæ‰‹æŸ”ã‚‰ã‹ã«ã€ãŠè©±ã—ã¦ãã ã•ã‚‹ã¨å¬‰ã—ã„ã§ã™ã€‚",
        "image": "2"
    },
    {
        "id": 3,
        "name": "Me-ya",
        "age": 22,
        "prefecture": "å²é˜œçœŒ",
        "tweet": "ã‚ˆã‚ã—ããŠé¡˜ã„ã—ã¾ã™ðŸ˜€ ã‚·ãƒ•ãƒˆåˆ¶ã§ä¸å®šä¼‘ã§ã™",
        "image": "3"
    },
    {
        "id": 4,
        "name": "é™½èœ",
        "age": 21,
        "prefecture": "èŒ¨åŸŽçœŒ",
        "tweet": "ãƒ‘ãƒ‘å‹Ÿé›†ã—ã¦ã„ã¾ã™ï¼ä¸€å…ã®ãƒžãƒžã§ã™ãŒå®œã—ããŠé¡˜ã„ã—ã¾ã™â•°(*Â´ï¸¶`*)â•¯è»Šã¯ãªã„ã§ã™(>_<;)",
        "image": "4"
    },
    {
        "id": 5,
        "name": "chiharuuuuu",
        "age": 23,
        "prefecture": "æ»‹è³€çœŒ",
        "tweet": "æ˜¨å¹´ã®4æœˆã‹ã‚‰ç¤¾ä¼šäººã¨ãªã‚Šã€æ»‹è³€çœŒã§ä¸€äººæš®ã‚‰ã—ã—ã¦ãŠã‚Šã¾ã™ã€‚(è¡Œå‹•ç¯„å›²ã¯å…µåº«ï½¥å¤§é˜ªï½¥äº¬éƒ½ï½¥æ»‹è³€çœŒã§ã™)",
        "image": "5"
    },
]
